{
  "name": "__qna__eyrr07bd3s_como_puedo_obtener_informaci_n_de_los_beneficios_q",
  "contexts": [
    "regular"
  ],
  "utterances": {
    "es": [
      "¿Cómo puedo obtener información de los beneficios que puedo obtener?",
      "Información sobre beneficios estudiantiles",
      "¿A qué beneficios puedo postular?",
      "Postulación a beneficios estudiantiles",
      "¿Qué beneficios estudiantiles podría tener?",
      "¿Cómo postulo a los beneficios estudiantiles?",
      "¿Cómo renuevo mis beneficios?",
      "Necesito renovar mis beneficios estudiantiles",
      "Información sobre las becas",
      "¿A qué becas puedo postular?",
      "¿Cómo renuevo mis becas?",
      "¿En que fecha debo renovar los beneficios estudiantiles?",
      "¿En qué fecha debo renovar mis beneficios?",
      "¿Cuándo tengo que renovar beneficios?",
      "¿Cuándo tengo que renovar mis becas?",
      "Quiero saber sobre el crédito interno",
      "Crédito interno de la UCM",
      "Beneficios estudiantiles",
      "Credito Interno de la Universidad",
      "Credito interno",
      "¿Cuando tengo que renovar mis becas?",
      "¿En que fecha debo renovar mis beneficios?",
      "¿A que beneficios puedo postular?",
      "¿Como puedo obtener información de los beneficios que puedo obtener?",
      "Deseo saber sobre los beneficios estudiantiles",
      "Deseo saber sobre becas y creditos",
      "Informacion sobre beneficios estudiantiles",
      "Postulacion a beneficios estudiantiles",
      "¿Que beneficios estudiantiles podria tener?",
      "¿Como postulo a los beneficios estudiantiles?",
      "¿Cuando tengo que renovar beneficios?",
      "Fecha máxima para postular a becas y créditos",
      "Fecha límite para postular a beneficios"
    ]
  },
  "slots": []
}